knot_exporter/__init__.py
knot_exporter/knot_exporter.py
knot_exporter-3.3.10.1.dist-info/METADATA
knot_exporter-3.3.10.1.dist-info/WHEEL
knot_exporter-3.3.10.1.dist-info/entry_points.txt
knot_exporter-3.3.10.1.dist-info/RECORD
